<annotation>
	<folder>licencesDataSet</folder>
	<filename>6.jpg</filename>
	<path>/home/kh/Documents/temp/opencv/licencesDataSet/6.jpg</path>
	<source>
		<database>Unknown</database>
	</source>
	<size>
		<width>800</width>
		<height>533</height>
		<depth>3</depth>
	</size>
	<segmented>0</segmented>
	<object>
		<name>licence-plate</name>
		<pose>Unspecified</pose>
		<truncated>0</truncated>
		<difficult>0</difficult>
		<bndbox>
			<xmin>97</xmin>
			<ymin>222</ymin>
			<xmax>163</xmax>
			<ymax>240</ymax>
		</bndbox>
	</object>
	<object>
		<name>licence-plate</name>
		<pose>Unspecified</pose>
		<truncated>0</truncated>
		<difficult>0</difficult>
		<bndbox>
			<xmin>458</xmin>
			<ymin>190</ymin>
			<xmax>542</xmax>
			<ymax>208</ymax>
		</bndbox>
	</object>
</annotation>
